Workbook

Sheet Entête
A11: Assuré :
A14: Adresse :
A17: Complété le :
A18: Par :
A20: Mis à jour le :
A21: Par :
A23: 1. | B23: Le Groupe Estrie-Richelieu vous offre ce document afin de vous aider à déterminer la valeur de vos biens, dans le but de vous permettre de vérifier si vos limites d'assurances sont adéquates.
A26: 2. | B26: Cet inventaire vous évitera peut-être de devenir COASSUREUR en sous-estimant la valeur assurable de vos biens. Certaines protections vous obligent à maintenir un montant minimum.
A29: 3. | B29: Ce document a été conçu dans votre intérêt. Cependant, il n'engage aucunement le Groupe Estrie-Richelieu et il ne peut lui être opposable.
A32: 4. | B32: Nous vous recommandons fortement de prendre le temps de le COMPLÉTER et de le CONSERVER en lieu sûr. Il vous suffira par la suite d'en faire une révision régulière pour préserver votre tranquillité d'esprit. Aucune obligation ne s'y rattache.
A36: 5. | B36: Votre représentant du Groupe Estrie-Richelieu se fera un plaisir de vous aider, que ce soit pour le compléter ou le réviser. N'hésitez pas à communiquer avec lui.
A39: RÉSUMÉ : | C39: Compléter les différentes pages et les montants seront reportés dans ce tableau par code couleur
A40: Instruments agricoles (excluant ceux pour travaux rémunérés) | I40: =IF('Équipement mobile (suite...)'!H51=0,"",'Équipement mobile (suite...)'!H51+'Instruments automoteurs'!G16+'Instruments automoteurs'!G49)
A41: Instruments agricole (utilisés pour travaux à l'extérieur) | I41: =IF('Équipement mobile (suite...)'!I51=0,"",'Équipement mobile (suite...)'!I51+'Instruments automoteurs'!H16+'Instruments automoteurs'!H49)
A42: Équipements de bâtiment | I42: =IF('Équipements de bâtiment'!I62=0,"",'Équipements de bâtiment'!I62)
A43: Produits de ferme et intrants (montant global) | I43: =IF('Équipements divers'!H49=0,"",'Équipements divers'!H49)
A44: Bovins (montant global) | I44: =IF(Animaux!F15=0,"",Animaux!F15)
A45: Porcs (montant global) | I45: =IF(Animaux!F28=0,"",Animaux!F28)
A46: Volailles (montant global) | I46: =IF(Animaux!F39=0,"",Animaux!F39)
A47: Chevaux | I47: =Animaux!F45
A48: =Animaux!A46 -> Chèvres | I48: =Animaux!F46
A49: =Animaux!A47 -> Moutons | I49: =Animaux!F47
A50: Autruches, émeus | I50: =Animaux!F48
A51: =IF(Animaux!B49="","",Animaux!B49) | I51: =Animaux!F49
A52: Équipement de bureau et informatique | I52: =IF('Équipements divers'!H12=0,"",'Équipements divers'!H12)

Sheet Équipement mobile
A1: Équipement mobile
A3: Les instruments automoteurs (tracteur, moissonneuse, …) font l'objet d'un onglet distinct. | H3: Pour travaux chez l'Assuré seulement | I3: Ou utilisé pour des travaux à l'extérieur
A4: Articles | C4: Année | D4: Année de | G4: Montant payé | H4: Valeur dépréciée* | I4: Valeur dépréciée*
C5: d'achat | D5: fabrication | E5: Marque | F5: Modèle | G5: $ | H5: $ | I5: $
A6: Aérateur de sol
A7: Alternateur (génératrice)
A8: Arracheuse de pommes de terre
A9: Arroseuse
A10: Benne basculante
A11: Chaînes
A12: Chargeuse à bois sur remorque
A13: Charrue
A14: Chisel (vibroculteur)
A15: Compresseur à air
A16: Convoyeur (monte-balles)
A17: Cultivateur
... A58: * La valeur à mentionner pour les équipements achetés neufs, il y a 5 ans ou moins, est le coût de remplacement.

Sheet Équipement mobile (suite...)
A1: Équipement Mobile (suite…)
A3: Les instruments automoteurs (tracteurs, moissonneuse, …) font l'objet d'un onglet distinct. | H3: Pour travaux chez l'Assuré seulement | I3: Ou utilisé pour des travaux à l'extérieur
A4: Articles | C4: Année | D4: Année de | G4: Montant payé | H4: Valeur dépréciée* | I4: Valeur dépréciée*
C5: d'achat | D5: fabrication | E5: Marque | F5: Modèle | G5: $ | H5: $ | I5: $
A6: Pulvérisateur / arroseuse
A7: Râteau à foin (andaineuse)
A8: Râteau à roches
A9: Remorque à bascule
A10: Retourneur d'andain
A11: Rigoleuse
A12: Rotoculteur
A13: Rouleau
A14: Rouleuse à grain
A15: Sableuse
A16: Sarcleur
A17: Scie mécanique
... A38: Autres : (précisez)
D51: Total : | H51: =SUM(H6:H50)+SUM('Équipement mobile'!H6:H57) -> 0 | I51: =SUM(I6:I50)+SUM('Équipement mobile'!I6:I57) -> 0
A52: * La valeur à mentionner pour les équipements achetés neufs, il y a 5 ans ou moins, est le coût de remplacement.

Sheet Instruments automoteurs
A1: Tracteurs & Équipement connexe
A3: (Inclure la valeur de la cabine, de la pelle, de la rétrocaveuse et autres équipements fixés en permanence qui ont été ajoutés) | G3: Pour travaux chez l'Assuré seulement | H3: Ou utilisé pour des travaux à l'extérieur
A4: Marque | C4: Modèle | D4: Année | E4: Année de | F4: Payé | G4: Valeur dépréciée* | H4: Valeur dépréciée*
D5: d'achat | E5: fabrication | F5: $ | G5: $ | H5: $
E16: Total : | G16: =SUM(G6:G15) -> 0 | H16: =SUM(H6:H15) -> 0
A18: Instruments automoteurs & Équipement connexe
A20: (Inclure la valeur des équipements fixés en permanence qui ont été ajoutés) | G20: Pour travaux chez l'Assuré seulement | H20: Ou utilisé pour des travaux à l'extérieur
A21: Articles | C21: Description | D21: Année | E21: Année de | F21: Payé | G21: Valeur dépréciée* | H21: Valeur dépréciée*
D22: d'achat | E22: fabrication | F22: $ | G22: $ | H22: $
A23: Andaineuse automotrice
A24: Chariot élévateur
A25: Ensileuse automotrice
A26: Faucheuse-conditionn. automotrice
A27: Véhicule utilitaire (à usage agricole exclusivement)**
A28: Moissonneuse-batteuse**
A29: - nez à maïs**
A30: - table à céréales**
A31: - GPS**
A32: Récolteuse à légumes
A33: Autres : (précisez)
A49: ** Ces instruments doivent être assurés spécifiquement. | E49: Total : | G49: =SUM(G25:G48) -> 0 | H49: 0
A50: * La valeur à mentionner pour les équipements achetés neufs, il y a 5 ans ou moins, est le coût de remplacement.

Sheet Équipements de bâtiment
A1: Équipement de Bâtiment
A3: Articles | C3: Préciser le bâtiment | H3: Montant payé | I3: Coût de rempla-
C4: dans lequel l'équipement se trouve | H4: $ | I4: cement ($)
A5: Abreuvoir
A6: Balai mécanisé
A7: Balance
A8: Bassin refroidisseur
A9: Benne à moulée
A10: Cages d'animaux
A11: Chariot à moulée
A12: Chauffe-eau
A13: Chaufferette
A14: Compresseur
A15: Concentrateur d'eau d'érable
A16: Convoyeur à chaîne
... A29: Laveuse à tubulure
A30: Équipements de bureau | C30: Ces biens doivent être mentionnés dans l'onglet "Équipements divers".
A31: Ordinateur
A32: Osmose
A33: Pompe à eau
A34: Pompe à piston
A35: Réservoir à lait
A36: Robot de traite
A37: Salon de traite
A38: Séchoir (à foin)
A39: Soigneur automatique
A40: Stalles
A41: Système de traite
A42: Tapis à vaches
... A46: Autres : (précisez)
H62: Total : | I62: =SUM(I5:I61) -> 0

Sheet Équipements divers
A1: Équipement de Bureau et Informatique
A3: Articles | B3: Marque | C3: Modèle | D3: Année | E3: Année de | F3: Montant payé | G3: Dans quel bâtiment | H3: Valeur dépréciée
D4: d'achat | E4: fabrication | F4: $ | G4: se trouve-t-il | H4: $
F12: Total : | H12: =SUM(H5:H11) -> 0
A14: Produits & Intrants
A16: Description | D16: Prix unitaire | F16: Quantité | H16: Valeur
F17: maximale | H17: maximale
A18: Biostat* | H18: =IF(D18="","",D18*F18)
A19: Bois de foyer (vente) (maximum 100 cordes) | H19: =IF(D19="","",D19*F19)
A20: Bois de service | H20: =IF(D20="","",D20*F20)
A21: Contenants | H21: =IF(D21="","",D21*F21)
A22: Embryons non implantés* | H22: =IF(D22="","",D22*F22)
A23: Engrais - Fertillisant | H23: =IF(D23="","",D23*F23)
A24: Essence - Diésel | H24: =IF(D24="","",D24*F24)
A25: Foin | H25: =IF(D25="","",D25*F25)
A26: Fourrage | H26: =IF(D26="","",D26*F26)
A27: Fruits | H27: =IF(D27="","",D27*F27)
A28: Grains - Semences | H28: =IF(D28="","",D28*F28)
A29: Huile - Lubrifiant | H29: =IF(D29="","",D29*F29)
... A41: Autres : (précisez) | H41: =IF(D41="","",D41*F41)
H42: =IF(D42="","",D42*F42)
H43: =IF(D43="","",D43*F43)
H44: =IF(D44="","",D44*F44)
H45: =IF(D45="","",D45*F45)
H46: =IF(D46="","",D46*F46)
H47: =IF(D47="","",D47*F47)
H48: =IF(D48="","",D48*F48)
A49: * Ces biens doivent être assurés spécifiquement. | G49: Total : | H49: =SUM(H18:H48) -> 0

Sheet Animaux
A1: Animaux
A3: Description | C3: Nombre | D3: Valeur moyenne | F3: Valeur totale
A6: BOVINS | B6: laitiers (max. 25 000 $/animal) ; boucherie (max. 10 000 $/animal)
A7: Vaches | F7: =IF(C7="","",+C7*D7)
A8: Taures (non-saillies) | F8: =IF(C8="","",+C8*D8)
A9: Veaux | F9: =IF(C9="","",+C9*D9)
A10: Taureaux | F10: =IF(C10="","",+C10*D10)
A11: Bouvillons | F11: =IF(C11="","",+C11*D11)
A12: Autres : | F12: =IF(C12="","",+C12*D12)
F13: =IF(C13="","",+C13*D13)
F14: =IF(C14="","",+C14*D14)
D15: Total : | F15: =SUM(F7:F14) -> 0
A17: PORCS
A19: Description | C19: Nombre | D19: Valeur moyenne | F19: Valeur totale
A21: Porcelets | F21: =IF(C21="","",+C21*D21)
A22: Porcs | F22: =IF(C22="","",+C22*D22)
A23: Truies | F23: =IF(C23="","",+C23*D23)
A24: Verrats | F24: =IF(C24="","",+C24*D24)
A25: Autres : | F25: =IF(C25="","",+C25*D25)
F26: =IF(C26="","",+C26*D26)
F27: =IF(C27="","",+C27*D27)
D28: Total : | F28: =SUM(F21:F27) -> 0
A30: VOLAILLES
A32: Description | C32: Nombre | D32: Valeur moyenne | F32: Valeur totale
A34: Dindes | F34: =IF(C34="","",+C34*D34)
A35: Poulets de gril | F35: =IF(C35="","",+C35*D35)
A36: Poules pondeuses | F36: =IF(C36="","",+C36*D36)
A37: Autres : | F37: =IF(C37="","",+C37*D37)
F38: =IF(C38="","",+C38*D38)
D39: Total : | F39: =SUM(F34:F38) -> 0
A41: DIVERS
A43: Description | C43: Nombre | D43: Valeur moyenne | F43: Valeur totale
A45: Chevaux (maximum 10 000 $/animal) | F45: =IF(C45="","",+C45*D45)
A46: Chèvres | F46: =IF(C46="","",+C46*D46)
A47: Moutons | F47: =IF(C47="","",+C47*D47)
A48: Autruches, émeus (max. 5 000$/animal) | F48: =IF(C48="","",+C48*D48)
A49: Autres : | F49: =IF(C49="","",+C49*D49)
D50: Total : | F50: =SUM(F45:F49) -> 0
A52: Les animaux dont la valeur dépasse les limites maximales indiquées doivent être référés à l'assureur.
